prodperfect/__init__.py
prodperfect/admin.py
prodperfect/apps.py
prodperfect/models.py
prodperfect/settings.py
prodperfect/views.py
prodperfect/templates/prodperfect/tracking_snippet.html
prodperfect/templatetags/__init__.py
prodperfect/templatetags/prodperfect.py
django_prodperfect-0.2.0.dist-info/METADATA
django_prodperfect-0.2.0.dist-info/WHEEL
django_prodperfect-0.2.0.dist-info/top_level.txt
django_prodperfect-0.2.0.dist-info/RECORD
