Metadata-Version: 2.1
Name: django-prodperfect
Version: 0.2.0
Summary: Django template tags for ProdPerfect tracking snippet
Home-page: https://github.com/ProdPerfect/django-prodperfect
Author: Lemuel Boyce
Author-email: lemuel@prodperfect.com
License: MIT
Platform: UNKNOWN
Classifier: Programming Language :: Python :: 3
Classifier: Programming Language :: Python :: 3.6
Classifier: Programming Language :: Python :: 3.7
Classifier: Operating System :: OS Independent
Requires-Dist: django (<3,>=2)
